{
    "kind": "youtubeAnalytics#resultTable",
    "columnHeaders": [
      {
        "name": "day",
        "columnType": "DIMENSION",
        "dataType": "STRING"
      },
      {
        "name": "views",
        "columnType": "METRIC",
        "dataType": "INTEGER"
      },
      {
        "name": "comments",
        "columnType": "METRIC",
        "dataType": "INTEGER"
      },
      {
        "name": "likes",
        "columnType": "METRIC",
        "dataType": "INTEGER"
      },
      {
        "name": "dislikes",
        "columnType": "METRIC",
        "dataType": "INTEGER"
      },
      {
        "name": "estimatedMinutesWatched",
        "columnType": "METRIC",
        "dataType": "INTEGER"
      },
      {
        "name": "averageViewDuration",
        "columnType": "METRIC",
        "dataType": "INTEGER"
      }
    ],
    "rows": [
      [
        "2018-10-01",
        4880,
        12,
        32,
        8,
        14524,
        178
      ],
      [
        "2018-10-02",
        4544,
        4,
        15,
        4,
        14530,
        191
      ],
      [
        "2018-10-03",
        4083,
        3,
        28,
        8,
        12655,
        185
      ],
      [
        "2018-10-04",
        4229,
        4,
        24,
        9,
        11646,
        165
      ],
      [
        "2018-10-05",
        4417,
        6,
        57,
        12,
        12085,
        164
      ],
      [
        "2018-10-06",
        4681,
        7,
        30,
        13,
        14034,
        179
      ],
      [
        "2018-10-07",
        8025,
        38,
        312,
        36,
        29105,
        217
      ],
      [
        "2018-10-08",
        9819,
        57,
        412,
        44,
        41447,
        253
      ],
      [
        "2018-10-09",
        7307,
        16,
        160,
        19,
        27314,
        224
      ],
      [
        "2018-10-10",
        7721,
        42,
        225,
        23,
        28781,
        223
      ],
      [
        "2018-10-11",
        5411,
        16,
        89,
        14,
        16925,
        187
      ],
      [
        "2018-10-12",
        4254,
        8,
        32,
        11,
        12052,
        169
      ],
      [
        "2018-10-13",
        4564,
        8,
        25,
        8,
        13762,
        180
      ],
      [
        "2018-10-14",
        8979,
        45,
        326,
        18,
        50225,
        335
      ],
      [
        "2018-10-15",
        7151,
        18,
        117,
        10,
        31622,
        265
      ],
      [
        "2018-10-16",
        6466,
        40,
        212,
        16,
        31145,
        289
      ],
      [
        "2018-10-17",
        5594,
        10,
        100,
        11,
        23449,
        251
      ],
      [
        "2018-10-18",
        4231,
        6,
        43,
        2,
        13975,
        198
      ],
      [
        "2018-10-19",
        4013,
        1,
        26,
        5,
        12302,
        183
      ]
    ]
  }